[{"type":"startNextRound","time":697542.8850000026,"round":23,"trial":27,"mouse":false},{"type":"startNextRound","time":697543.1400000015,"round":24,"trial":27,"mouse":false},{"type":"startNextRound","time":699517.1200000005,"round":19,"trial":28,"mouse":false},{"type":"keydown","time":699517.4250000018,"key":"k","mouse":false,"round":19,"trial":28},{"type":"keyup","time":699740.78,"key":"k","mouse":false,"round":19,"trial":28},{"type":"keydown","time":699957.9550000017,"key":"g","mouse":false,"round":19,"trial":28},{"type":"keyup","time":700174.0649999992,"key":"g","mouse":false,"round":19,"trial":28},{"type":"keydown","time":700349.3850000014,"key":"j","mouse":false,"round":19,"trial":28},{"type":"keyup","time":700559.5200000026,"key":"j","mouse":false,"round":19,"trial":28},{"type":"keydown","time":700711.0549999997,"key":"h","mouse":false,"round":19,"trial":28},{"type":"keyup","time":700924.1250000014,"key":"h","mouse":false,"round":19,"trial":28},{"type":"correctSequence","time":700924.2750000012,"sequence":"kgjh","round":19,"trial":28,"mouse":false},{"type":"winRound","time":700924.3000000024,"round":19,"trial":28,"mouse":false,"activeProbability":0.5,"sequence":"kgjh","unchosenProbability":0.5,"mcsScore":0.6395850113935069},{"type":"startNextRound","time":700924.3950000019,"round":21,"trial":28,"mouse":false},{"type":"startNextRound","time":703925.1050000021,"round":23,"trial":28,"mouse":false},{"type":"startNextRound","time":703925.3649999992,"round":24,"trial":28,"mouse":false},{"type":"startNextRound","time":704851.2450000016,"round":19,"trial":29,"mouse":false},{"type":"keydown","time":704851.5100000005,"key":"g","mouse":false,"round":19,"trial":29},{"type":"keyup","time":705064.330000001,"key":"g","mouse":false,"round":19,"trial":29},{"type":"keydown","time":705230.2100000016,"key":"j","mouse":false,"round":19,"trial":29},{"type":"keyup","time":705470.3800000024,"key":"j","mouse":false,"round":19,"trial":29},{"type":"keydown","time":705574.9099999993,"key":"h","mouse":false,"round":19,"trial":29},{"type":"keyup","time":705749.490000002,"key":"h","mouse":false,"round":19,"trial":29},{"type":"keydown","time":705897.2549999999,"key":"k","mouse":false,"round":19,"trial":29},{"type":"keyup","time":706087.7400000027,"key":"k","mouse":false,"round":19,"trial":29},{"type":"correctSequence","time":706087.8850000008,"sequence":"gjhk","round":19,"trial":29,"mouse":false},{"type":"lostRound","time":706087.9050000003,"round":19,"trial":29,"mouse":false,"activeProbability":0.5,"sequence":"gjhk","unchosenProbability":0.5,"mcsScore":0.6389929410183359},{"type":"startNextRound","time":706087.9650000024,"round":20,"trial":29,"mouse":false},{"type":"startNextRound","time":709088.8799999993,"round":23,"trial":29,"mouse":false},{"type":"startNextRound","time":709089.1450000018,"round":24,"trial":29,"mouse":false},{"type":"startNextRound","time":714431.9250000007,"round":19,"trial":30,"mouse":false},{"type":"keydown","time":714432.3000000004,"key":"k","mouse":false,"round":19,"trial":30},{"type":"keyup","time":714651.9299999999,"key":"k","mouse":false,"round":19,"trial":30},{"type":"keydown","time":714853.3549999993,"key":"g","mouse":false,"round":19,"trial":30},{"type":"keyup","time":715080.2100000001,"key":"g","mouse":false,"round":19,"trial":30},{"type":"keydown","time":715217.1750000016,"key":"j","mouse":false,"round":19,"trial":30},{"type":"keyup","time":715460.7600000018,"key":"j","mouse":false,"round":19,"trial":30},{"type":"keydown","time":715579.5099999995,"key":"h","mouse":false,"round":19,"trial":30},{"type":"keyup","time":715797.4700000014,"key":"h","mouse":false,"round":19,"trial":30},{"type":"correctSequence","time":715797.5450000013,"sequence":"kgjh","round":19,"trial":30,"mouse":false},{"type":"winRound","time":715797.5600000027,"round":19,"trial":30,"mouse":false,"activeProbability":0.5,"sequence":"kgjh","unchosenProbability":0.5,"mcsScore":0.7966938968074602},{"type":"startNextRound","time":715797.6149999995,"round":21,"trial":30,"mouse":false},{"type":"startNextRound","time":718797.9599999998,"round":23,"trial":30,"mouse":false},{"type":"startNextRound","time":718798.1900000013,"round":24,"trial":30,"mouse":false},{"type":"startNextRound","time":726324.9649999999,"round":19,"trial":31,"mouse":false},{"type":"keydown","time":726325.2749999992,"key":"k","mouse":false,"round":19,"trial":31},{"type":"keyup","time":726542.4550000025,"key":"k","mouse":false,"round":19,"trial":31},{"type":"keydown","time":726709.1450000007,"key":"g","mouse":false,"round":19,"trial":31},{"type":"keyup","time":726938.3500000003,"key":"g","mouse":false,"round":19,"trial":31},{"type":"keydown","time":727022.3850000002,"key":"j","mouse":false,"round":19,"trial":31},{"type":"keyup","time":727229.3150000005,"key":"j","mouse":false,"round":19,"trial":31},{"type":"keydown","time":727304.7350000015,"key":"h","mouse":false,"round":19,"trial":31},{"type":"keyup","time":727521.7499999999,"key":"h","mouse":false,"round":19,"trial":31},{"type":"correctSequence","time":727521.8300000015,"sequence":"kgjh","round":19,"trial":31,"mouse":false},{"type":"lostRound","time":727521.8449999993,"round":19,"trial":31,"mouse":false,"activeProbability":0.5,"sequence":"kgjh","unchosenProbability":0.5,"mcsScore":0.29454971990801426},{"type":"startNextRound","time":727522.8650000027,"round":20,"trial":31,"mouse":false},{"type":"startNextRound","time":730523.2099999994,"round":23,"trial":31,"mouse":false},{"type":"startNextRound","time":730523.4750000017,"round":24,"trial":31,"mouse":false},{"type":"startNextRound","time":732563.6799999992,"round":19,"trial":32,"mouse":false},{"type":"keydown","time":732563.9499999997,"key":"g","mouse":false,"round":19,"trial":32},{"type":"keyup","time":732746.5800000028,"key":"g","mouse":false,"round":19,"trial":32},{"type":"keydown","time":732936.1700000009,"key":"j","mouse":false,"round":19,"trial":32},{"type":"keyup","time":733132.4750000022,"key":"j","mouse":false,"round":19,"trial":32},{"type":"keydown","time":733289.1550000022,"key":"h","mouse":false,"round":19,"trial":32},{"type":"keyup","time":733456.9000000011,"key":"h","mouse":false,"round":19,"trial":32},{"type":"keydown","time":733628.3350000012,"key":"k","mouse":false,"round":19,"trial":32},{"type":"keyup","time":733792.7550000022,"key":"k","mouse":false,"round":19,"trial":32},{"type":"correctSequence","time":733792.8350000002,"sequence":"gjhk","round":19,"trial":32,"mouse":false},{"type":"winRound","time":733792.8500000016,"round":19,"trial":32,"mouse":false,"activeProbability":0.5,"sequence":"gjhk","unchosenProbability":0.5,"mcsScore":0.12018318397109828},{"type":"startNextRound","time":733792.9100000001,"round":21,"trial":32,"mouse":false}]