[{"type":"startNextRound","time":1189040.8400000015,"round":23,"trial":107,"mouse":false},{"type":"startNextRound","time":1189041.0849999897,"round":24,"trial":107,"mouse":false},{"type":"startNextRound","time":1189571.2199999979,"round":19,"trial":108,"mouse":false},{"type":"keydown","time":1189571.4299999964,"key":"k","mouse":false,"round":19,"trial":108},{"type":"keyup","time":1189759.229999996,"key":"k","mouse":false,"round":19,"trial":108},{"type":"keydown","time":1189914.1649999947,"key":"g","mouse":false,"round":19,"trial":108},{"type":"keyup","time":1190042.4149999889,"key":"g","mouse":false,"round":19,"trial":108},{"type":"keydown","time":1190273.2049999903,"key":"j","mouse":false,"round":19,"trial":108},{"type":"keyup","time":1190426.3299999875,"key":"j","mouse":false,"round":19,"trial":108},{"type":"keydown","time":1190581.1949999915,"key":"h","mouse":false,"round":19,"trial":108},{"type":"keyup","time":1190750.239999994,"key":"h","mouse":false,"round":19,"trial":108},{"type":"correctSequence","time":1190750.3099999884,"sequence":"kgjh","round":19,"trial":108,"mouse":false},{"type":"lostRound","time":1190750.3399999987,"round":19,"trial":108,"mouse":false,"activeProbability":0.5,"sequence":"kgjh","unchosenProbability":0.5,"mcsScore":0.25680190207397646},{"type":"startNextRound","time":1190750.4799999879,"round":20,"trial":108,"mouse":false},{"type":"startNextRound","time":1193753.1249999884,"round":23,"trial":108,"mouse":false},{"type":"startNextRound","time":1193753.31,"round":24,"trial":108,"mouse":false},{"type":"startNextRound","time":1194179.799999998,"round":19,"trial":109,"mouse":false},{"type":"keydown","time":1194179.9699999974,"key":"k","mouse":false,"round":19,"trial":109},{"type":"keyup","time":1194398.8699999899,"key":"k","mouse":false,"round":19,"trial":109},{"type":"keydown","time":1194548.6349999993,"key":"g","mouse":false,"round":19,"trial":109},{"type":"keyup","time":1194711.7949999957,"key":"g","mouse":false,"round":19,"trial":109},{"type":"keydown","time":1194901.8649999925,"key":"j","mouse":false,"round":19,"trial":109},{"type":"keyup","time":1195070.8650000016,"key":"j","mouse":false,"round":19,"trial":109},{"type":"keydown","time":1195194.8899999987,"key":"h","mouse":false,"round":19,"trial":109},{"type":"keyup","time":1195378.8499999936,"key":"h","mouse":false,"round":19,"trial":109},{"type":"correctSequence","time":1195378.9099999995,"sequence":"kgjh","round":19,"trial":109,"mouse":false},{"type":"winRound","time":1195378.9299999918,"round":19,"trial":109,"mouse":false,"activeProbability":0.5,"sequence":"kgjh","unchosenProbability":0.5,"mcsScore":0.8347283090358373},{"type":"startNextRound","time":1195378.9949999917,"round":21,"trial":109,"mouse":false},{"type":"startNextRound","time":1198392.0549999895,"round":23,"trial":109,"mouse":false},{"type":"startNextRound","time":1198392.3099999956,"round":24,"trial":109,"mouse":false},{"type":"startNextRound","time":1198923.4949999955,"round":19,"trial":110,"mouse":false},{"type":"keydown","time":1198923.6549999914,"key":"k","mouse":false,"round":19,"trial":110},{"type":"keyup","time":1199112.049999996,"key":"k","mouse":false,"round":19,"trial":110},{"type":"keydown","time":1199267.5499999896,"key":"g","mouse":false,"round":19,"trial":110},{"type":"keyup","time":1199425.9400000009,"key":"g","mouse":false,"round":19,"trial":110},{"type":"keydown","time":1199605.739999999,"key":"j","mouse":false,"round":19,"trial":110},{"type":"keyup","time":1199769.969999994,"key":"j","mouse":false,"round":19,"trial":110},{"type":"keydown","time":1199895.525,"key":"h","mouse":false,"round":19,"trial":110},{"type":"keyup","time":1200063.2599999954,"key":"h","mouse":false,"round":19,"trial":110},{"type":"correctSequence","time":1200063.3249999955,"sequence":"kgjh","round":19,"trial":110,"mouse":false},{"type":"lostRound","time":1200063.3499999968,"round":19,"trial":110,"mouse":false,"activeProbability":0.5,"sequence":"kgjh","unchosenProbability":0.5,"mcsScore":0.08350557155393479},{"type":"startNextRound","time":1200063.4250000003,"round":20,"trial":110,"mouse":false},{"type":"startNextRound","time":1203071.8249999918,"round":23,"trial":110,"mouse":false},{"type":"startNextRound","time":1203071.9499999979,"round":24,"trial":110,"mouse":false},{"type":"startNextRound","time":1203280.1099999924,"round":19,"trial":111,"mouse":false},{"type":"keydown","time":1203280.2699999884,"key":"k","mouse":false,"round":19,"trial":111},{"type":"keyup","time":1203513.4049999905,"key":"k","mouse":false,"round":19,"trial":111},{"type":"keydown","time":1203662.7799999989,"key":"g","mouse":false,"round":19,"trial":111},{"type":"keyup","time":1203832.2399999888,"key":"g","mouse":false,"round":19,"trial":111},{"type":"keydown","time":1204026.174999992,"key":"j","mouse":false,"round":19,"trial":111},{"type":"keyup","time":1204230.2049999998,"key":"j","mouse":false,"round":19,"trial":111},{"type":"keydown","time":1204307.9299999955,"key":"h","mouse":false,"round":19,"trial":111},{"type":"keyup","time":1204528.655000002,"key":"h","mouse":false,"round":19,"trial":111},{"type":"correctSequence","time":1204528.7199999876,"sequence":"kgjh","round":19,"trial":111,"mouse":false},{"type":"winRound","time":1204528.7499999977,"round":19,"trial":111,"mouse":false,"activeProbability":0.5,"sequence":"kgjh","unchosenProbability":0.5,"mcsScore":0.9899400760123753},{"type":"startNextRound","time":1204528.8549999967,"round":21,"trial":111,"mouse":false},{"type":"startNextRound","time":1207534.0299999951,"round":23,"trial":111,"mouse":false},{"type":"startNextRound","time":1207534.2149999924,"round":24,"trial":111,"mouse":false},{"type":"startNextRound","time":1209418.3849999972,"round":19,"trial":112,"mouse":false},{"type":"keydown","time":1209418.8399999985,"key":"g","mouse":false,"round":19,"trial":112},{"type":"keyup","time":1209575.5999999964,"key":"g","mouse":false,"round":19,"trial":112},{"type":"keydown","time":1209735.17,"key":"j","mouse":false,"round":19,"trial":112},{"type":"keyup","time":1209909.8399999929,"key":"j","mouse":false,"round":19,"trial":112},{"type":"keydown","time":1210024.1799999932,"key":"h","mouse":false,"round":19,"trial":112},{"type":"keyup","time":1210219.219999999,"key":"h","mouse":false,"round":19,"trial":112},{"type":"keydown","time":1210382.2999999975,"key":"k","mouse":false,"round":19,"trial":112},{"type":"keyup","time":1210576.9449999933,"key":"k","mouse":false,"round":19,"trial":112},{"type":"correctSequence","time":1210577.019999997,"sequence":"gjhk","round":19,"trial":112,"mouse":false},{"type":"lostRound","time":1210577.0499999926,"round":19,"trial":112,"mouse":false,"activeProbability":0.1,"sequence":"gjhk","unchosenProbability":0.9,"mcsScore":0.35436269023169675},{"type":"startNextRound","time":1210577.1349999995,"round":20,"trial":112,"mouse":false}]