[{"type":"startNextRound","time":2158383.72,"round":23,"trial":107,"mouse":false},{"type":"startNextRound","time":2158383.9150000005,"round":24,"trial":107,"mouse":false},{"type":"startNextRound","time":2159046.345,"round":19,"trial":108,"mouse":false},{"type":"keydown","time":2159046.5900000003,"key":"g","mouse":false,"round":19,"trial":108},{"type":"keyup","time":2159160.2850000006,"key":"g","mouse":false,"round":19,"trial":108},{"type":"keyup","time":2159160.4250000003,"key":"g","mouse":false,"round":19,"trial":108},{"type":"keyup","time":2159160.4950000006,"key":"g","mouse":false,"round":19,"trial":108},{"type":"keydown","time":2159361.035,"key":"j","mouse":false,"round":19,"trial":108},{"type":"keyup","time":2159471.9150000005,"key":"j","mouse":false,"round":19,"trial":108},{"type":"keyup","time":2159472.0700000003,"key":"j","mouse":false,"round":19,"trial":108},{"type":"keyup","time":2159472.16,"key":"j","mouse":false,"round":19,"trial":108},{"type":"keydown","time":2159602.5100000002,"key":"h","mouse":false,"round":19,"trial":108},{"type":"keyup","time":2159702.3750000005,"key":"h","mouse":false,"round":19,"trial":108},{"type":"keyup","time":2159702.4800000004,"key":"h","mouse":false,"round":19,"trial":108},{"type":"keyup","time":2159702.535,"key":"h","mouse":false,"round":19,"trial":108},{"type":"keydown","time":2160252.4650000003,"key":"k","mouse":false,"round":19,"trial":108},{"type":"keyup","time":2160410.9850000003,"key":"k","mouse":false,"round":19,"trial":108},{"type":"correctSequence","time":2160411.0450000004,"sequence":"gjhk","round":19,"trial":108,"mouse":false},{"type":"winRound","time":2160411.0650000004,"round":19,"trial":108,"mouse":false,"activeProbability":0.7,"sequence":"gjhk","unchosenProbability":0.30000000000000004,"mcsScore":0.524870949224143},{"type":"startNextRound","time":2160411.1850000005,"round":21,"trial":108,"mouse":false},{"type":"startNextRound","time":2163420.7300000004,"round":23,"trial":108,"mouse":false},{"type":"startNextRound","time":2163420.97,"round":24,"trial":108,"mouse":false},{"type":"startNextRound","time":2164495.6300000004,"round":19,"trial":109,"mouse":false},{"type":"keydown","time":2164495.855,"key":"g","mouse":false,"round":19,"trial":109},{"type":"keyup","time":2164610.2750000004,"key":"g","mouse":false,"round":19,"trial":109},{"type":"keyup","time":2164610.4650000003,"key":"g","mouse":false,"round":19,"trial":109},{"type":"keyup","time":2164610.5450000004,"key":"g","mouse":false,"round":19,"trial":109},{"type":"keydown","time":2164835.7900000005,"key":"j","mouse":false,"round":19,"trial":109},{"type":"keyup","time":2164943.0900000003,"key":"j","mouse":false,"round":19,"trial":109},{"type":"keyup","time":2164943.1850000005,"key":"j","mouse":false,"round":19,"trial":109},{"type":"keyup","time":2164943.2300000004,"key":"j","mouse":false,"round":19,"trial":109},{"type":"keydown","time":2165075.8350000004,"key":"h","mouse":false,"round":19,"trial":109},{"type":"keyup","time":2165206.81,"key":"h","mouse":false,"round":19,"trial":109},{"type":"keyup","time":2165206.9800000004,"key":"h","mouse":false,"round":19,"trial":109},{"type":"keyup","time":2165207.1100000003,"key":"h","mouse":false,"round":19,"trial":109},{"type":"keydown","time":2165390.835,"key":"k","mouse":false,"round":19,"trial":109},{"type":"keyup","time":2165510.055,"key":"k","mouse":false,"round":19,"trial":109},{"type":"correctSequence","time":2165510.13,"sequence":"gjhk","round":19,"trial":109,"mouse":false},{"type":"winRound","time":2165510.1500000004,"round":19,"trial":109,"mouse":false,"activeProbability":0.7,"sequence":"gjhk","unchosenProbability":0.30000000000000004,"mcsScore":0.4483503496729755},{"type":"startNextRound","time":2165510.22,"round":21,"trial":109,"mouse":false},{"type":"startNextRound","time":2168512,"round":23,"trial":109,"mouse":false},{"type":"startNextRound","time":2168512.39,"round":24,"trial":109,"mouse":false},{"type":"startNextRound","time":2169612.5100000002,"round":19,"trial":110,"mouse":false},{"type":"keydown","time":2169612.8400000003,"key":"g","mouse":false,"round":19,"trial":110},{"type":"keyup","time":2169720.3000000003,"key":"g","mouse":false,"round":19,"trial":110},{"type":"keyup","time":2169720.4250000003,"key":"g","mouse":false,"round":19,"trial":110},{"type":"keyup","time":2169720.49,"key":"g","mouse":false,"round":19,"trial":110},{"type":"keydown","time":2169971.5750000007,"key":"j","mouse":false,"round":19,"trial":110},{"type":"keyup","time":2170107.1450000005,"key":"j","mouse":false,"round":19,"trial":110},{"type":"keyup","time":2170107.2800000003,"key":"j","mouse":false,"round":19,"trial":110},{"type":"keyup","time":2170107.325,"key":"j","mouse":false,"round":19,"trial":110},{"type":"keydown","time":2170234.4400000004,"key":"h","mouse":false,"round":19,"trial":110},{"type":"keyup","time":2170368.24,"key":"h","mouse":false,"round":19,"trial":110},{"type":"keyup","time":2170368.37,"key":"h","mouse":false,"round":19,"trial":110},{"type":"keyup","time":2170368.4800000004,"key":"h","mouse":false,"round":19,"trial":110},{"type":"keydown","time":2170569.3600000003,"key":"k","mouse":false,"round":19,"trial":110},{"type":"keyup","time":2170701.3300000005,"key":"k","mouse":false,"round":19,"trial":110},{"type":"correctSequence","time":2170701.4500000007,"sequence":"gjhk","round":19,"trial":110,"mouse":false},{"type":"lostRound","time":2170701.48,"round":19,"trial":110,"mouse":false,"activeProbability":0.7,"sequence":"gjhk","unchosenProbability":0.30000000000000004,"mcsScore":0.8873194566654348},{"type":"startNextRound","time":2170701.5700000003,"round":20,"trial":110,"mouse":false},{"type":"startNextRound","time":2173712.0200000005,"round":23,"trial":110,"mouse":false},{"type":"startNextRound","time":2173715.1050000004,"round":24,"trial":110,"mouse":false},{"type":"startNextRound","time":2174955.7350000003,"round":19,"trial":111,"mouse":false},{"type":"keydown","time":2174956.7400000007,"key":"g","mouse":false,"round":19,"trial":111},{"type":"keyup","time":2175045.4450000003,"key":"g","mouse":false,"round":19,"trial":111},{"type":"keyup","time":2175045.6100000003,"key":"g","mouse":false,"round":19,"trial":111},{"type":"keyup","time":2175045.6700000004,"key":"g","mouse":false,"round":19,"trial":111},{"type":"keydown","time":2175315.1250000005,"key":"j","mouse":false,"round":19,"trial":111},{"type":"keyup","time":2175441.7,"key":"j","mouse":false,"round":19,"trial":111},{"type":"keyup","time":2175441.8350000004,"key":"j","mouse":false,"round":19,"trial":111},{"type":"keyup","time":2175441.9000000004,"key":"j","mouse":false,"round":19,"trial":111},{"type":"keydown","time":2175561.3000000003,"key":"h","mouse":false,"round":19,"trial":111},{"type":"keyup","time":2175652.3800000004,"key":"h","mouse":false,"round":19,"trial":111},{"type":"keyup","time":2175652.5100000002,"key":"h","mouse":false,"round":19,"trial":111},{"type":"keyup","time":2175652.6100000003,"key":"h","mouse":false,"round":19,"trial":111},{"type":"keydown","time":2175837.2800000003,"key":"k","mouse":false,"round":19,"trial":111},{"type":"keyup","time":2175960.5700000003,"key":"k","mouse":false,"round":19,"trial":111},{"type":"correctSequence","time":2175960.8000000003,"sequence":"gjhk","round":19,"trial":111,"mouse":false},{"type":"winRound","time":2175960.8800000004,"round":19,"trial":111,"mouse":false,"activeProbability":0.7,"sequence":"gjhk","unchosenProbability":0.30000000000000004,"mcsScore":0.6388485666458632},{"type":"startNextRound","time":2175961.0250000004,"round":21,"trial":111,"mouse":false},{"type":"startNextRound","time":2178975.4300000006,"round":23,"trial":111,"mouse":false},{"type":"startNextRound","time":2178975.7,"round":24,"trial":111,"mouse":false},{"type":"startNextRound","time":2179549.4100000006,"round":19,"trial":112,"mouse":false},{"type":"keydown","time":2179549.87,"key":"g","mouse":false,"round":19,"trial":112},{"type":"keyup","time":2179667.3550000004,"key":"g","mouse":false,"round":19,"trial":112},{"type":"keyup","time":2179667.5150000006,"key":"g","mouse":false,"round":19,"trial":112},{"type":"keyup","time":2179667.585,"key":"g","mouse":false,"round":19,"trial":112},{"type":"keydown","time":2179867.66,"key":"j","mouse":false,"round":19,"trial":112},{"type":"keyup","time":2179983.8200000003,"key":"j","mouse":false,"round":19,"trial":112},{"type":"keyup","time":2179984.0150000006,"key":"j","mouse":false,"round":19,"trial":112},{"type":"keyup","time":2179984.095,"key":"j","mouse":false,"round":19,"trial":112},{"type":"keydown","time":2180150.9900000007,"key":"h","mouse":false,"round":19,"trial":112},{"type":"keyup","time":2180224.6400000006,"key":"h","mouse":false,"round":19,"trial":112},{"type":"keyup","time":2180224.7950000004,"key":"h","mouse":false,"round":19,"trial":112},{"type":"keyup","time":2180224.8600000003,"key":"h","mouse":false,"round":19,"trial":112},{"type":"keydown","time":2180431.7950000004,"key":"k","mouse":false,"round":19,"trial":112},{"type":"keyup","time":2180546.8200000003,"key":"k","mouse":false,"round":19,"trial":112},{"type":"correctSequence","time":2180546.9150000005,"sequence":"gjhk","round":19,"trial":112,"mouse":false},{"type":"winRound","time":2180546.9400000004,"round":19,"trial":112,"mouse":false,"activeProbability":0.7,"sequence":"gjhk","unchosenProbability":0.30000000000000004,"mcsScore":0.3794251836641851},{"type":"startNextRound","time":2180547.0650000004,"round":21,"trial":112,"mouse":false}]