[{"type":"startNextRound","time":1157389.0900000043,"round":23,"trial":12,"mouse":false},{"type":"startNextRound","time":1157389.375000006,"round":24,"trial":12,"mouse":false},{"type":"startNextRound","time":1160622.755000004,"round":19,"trial":13,"mouse":false},{"type":"keydown","time":1160623.0400000059,"key":"k","mouse":false,"round":19,"trial":13},{"type":"keyup","time":1160925.4950000031,"key":"k","mouse":false,"round":19,"trial":13},{"type":"keydown","time":1160957.5750000004,"key":"g","mouse":false,"round":19,"trial":13},{"type":"keydown","time":1160958.0250000071,"key":"k","mouse":false,"round":19,"trial":13},{"type":"keyup","time":1161005.845000007,"key":"k","mouse":false,"round":19,"trial":13},{"type":"keyup","time":1161133.8000000033,"key":"g","mouse":false,"round":19,"trial":13},{"type":"keydown","time":1161214.3600000055,"key":"j","mouse":false,"round":19,"trial":13},{"type":"keyup","time":1161405.5600000066,"key":"j","mouse":false,"round":19,"trial":13},{"type":"incorrectSequence","time":1161405.645000006,"sequence":"kgkj","round":19,"trial":13,"mouse":false},{"type":"incorrectPlay","time":1161405.6600000039,"round":19,"trial":13,"mouse":false,"activeProbability":0.1,"sequence":"kgjh","unchosenProbability":0.9,"mcsScore":0.37964751586344425},{"type":"startNextRound","time":1161405.795000006,"round":20,"trial":13,"mouse":false},{"type":"startNextRound","time":1164410.5000000054,"round":23,"trial":13,"mouse":false},{"type":"startNextRound","time":1164410.7150000054,"round":24,"trial":13,"mouse":false},{"type":"startNextRound","time":1167613.8900000006,"round":19,"trial":14,"mouse":false},{"type":"keydown","time":1167614.045000002,"key":"g","mouse":false,"round":19,"trial":14},{"type":"keyup","time":1167853.9200000013,"key":"g","mouse":false,"round":19,"trial":14},{"type":"keydown","time":1167950.245,"key":"j","mouse":false,"round":19,"trial":14},{"type":"keyup","time":1168174.015000004,"key":"j","mouse":false,"round":19,"trial":14},{"type":"keydown","time":1168285.870000007,"key":"h","mouse":false,"round":19,"trial":14},{"type":"keyup","time":1168477.515000006,"key":"h","mouse":false,"round":19,"trial":14},{"type":"keydown","time":1168654.1700000016,"key":"k","mouse":false,"round":19,"trial":14},{"type":"keyup","time":1168814.0100000019,"key":"k","mouse":false,"round":19,"trial":14},{"type":"correctSequence","time":1168814.0950000016,"sequence":"gjhk","round":19,"trial":14,"mouse":false},{"type":"lostRound","time":1168814.1150000012,"round":19,"trial":14,"mouse":false,"activeProbability":0.1,"sequence":"gjhk","unchosenProbability":0.9,"mcsScore":0.33272317739593693},{"type":"startNextRound","time":1168814.215000006,"round":20,"trial":14,"mouse":false},{"type":"startNextRound","time":1171821.195000004,"round":23,"trial":14,"mouse":false},{"type":"startNextRound","time":1171821.2950000016,"round":24,"trial":14,"mouse":false},{"type":"startNextRound","time":1176030.230000004,"round":19,"trial":15,"mouse":false},{"type":"keydown","time":1176030.325000007,"key":"k","mouse":false,"round":19,"trial":15},{"type":"keyup","time":1176317.6250000033,"key":"k","mouse":false,"round":19,"trial":15},{"type":"keydown","time":1176365.5350000043,"key":"k","mouse":false,"round":19,"trial":15},{"type":"keydown","time":1176397.6850000035,"key":"g","mouse":false,"round":19,"trial":15},{"type":"keyup","time":1176430.2300000053,"key":"k","mouse":false,"round":19,"trial":15},{"type":"keyup","time":1176573.2100000023,"key":"g","mouse":false,"round":19,"trial":15},{"type":"keydown","time":1176781.9100000053,"key":"j","mouse":false,"round":19,"trial":15},{"type":"keyup","time":1176974.0000000019,"key":"j","mouse":false,"round":19,"trial":15},{"type":"incorrectSequence","time":1176974.095000005,"sequence":"kkgj","round":19,"trial":15,"mouse":false},{"type":"incorrectPlay","time":1176974.110000003,"round":19,"trial":15,"mouse":false,"activeProbability":0.1,"sequence":"kgjh","unchosenProbability":0.9,"mcsScore":0.4507313107587152},{"type":"startNextRound","time":1176974.3050000034,"round":20,"trial":15,"mouse":false},{"type":"startNextRound","time":1179980.1000000006,"round":23,"trial":15,"mouse":false},{"type":"startNextRound","time":1179980.3200000024,"round":24,"trial":15,"mouse":false},{"type":"startNextRound","time":1181901.525000001,"round":19,"trial":16,"mouse":false},{"type":"keydown","time":1181901.6200000043,"key":"k","mouse":false,"round":19,"trial":16},{"type":"keyup","time":1182077.4850000017,"key":"k","mouse":false,"round":19,"trial":16},{"type":"keydown","time":1182285.9850000022,"key":"g","mouse":false,"round":19,"trial":16},{"type":"keyup","time":1182413.6150000049,"key":"g","mouse":false,"round":19,"trial":16},{"type":"keydown","time":1182574.1750000017,"key":"j","mouse":false,"round":19,"trial":16},{"type":"keyup","time":1182765.935000003,"key":"j","mouse":false,"round":19,"trial":16},{"type":"keydown","time":1182813.7950000018,"key":"h","mouse":false,"round":19,"trial":16},{"type":"keyup","time":1182957.7100000023,"key":"h","mouse":false,"round":19,"trial":16},{"type":"correctSequence","time":1182957.795000002,"sequence":"kgjh","round":19,"trial":16,"mouse":false},{"type":"winRound","time":1182957.8150000016,"round":19,"trial":16,"mouse":false,"activeProbability":0.1,"sequence":"kgjh","unchosenProbability":0.9,"mcsScore":0.6687702599354863},{"type":"startNextRound","time":1182957.9150000063,"round":21,"trial":16,"mouse":false},{"type":"startNextRound","time":1185963.475000004,"round":23,"trial":16,"mouse":false},{"type":"startNextRound","time":1185963.585000005,"round":24,"trial":16,"mouse":false},{"type":"startNextRound","time":1186413.7200000042,"round":19,"trial":17,"mouse":false},{"type":"keydown","time":1186413.8200000017,"key":"k","mouse":false,"round":19,"trial":17},{"type":"keyup","time":1186589.7600000026,"key":"k","mouse":false,"round":19,"trial":17},{"type":"keydown","time":1186717.6100000069,"key":"g","mouse":false,"round":19,"trial":17},{"type":"keyup","time":1186861.7550000055,"key":"g","mouse":false,"round":19,"trial":17},{"type":"keydown","time":1186973.4950000057,"key":"j","mouse":false,"round":19,"trial":17},{"type":"keyup","time":1187101.4150000047,"key":"j","mouse":false,"round":19,"trial":17},{"type":"keydown","time":1187213.635,"key":"h","mouse":false,"round":19,"trial":17},{"type":"keyup","time":1187357.7700000023,"key":"h","mouse":false,"round":19,"trial":17},{"type":"correctSequence","time":1187357.8400000043,"sequence":"kgjh","round":19,"trial":17,"mouse":false},{"type":"winRound","time":1187357.8600000036,"round":19,"trial":17,"mouse":false,"activeProbability":0.1,"sequence":"kgjh","unchosenProbability":0.9,"mcsScore":0.9159758324580021},{"type":"startNextRound","time":1187357.9200000023,"round":21,"trial":17,"mouse":false}]