[{"type":"startNextRound","time":1347729,"round":23,"trial":57,"mouse":false},{"type":"startNextRound","time":1347729,"round":24,"trial":57,"mouse":false},{"type":"startNextRound","time":1348290,"round":19,"trial":58,"mouse":false},{"type":"keydown","time":1348290,"key":"k","mouse":false,"round":19,"trial":58},{"type":"keyup","time":1348443,"key":"k","mouse":false,"round":19,"trial":58},{"type":"keydown","time":1348709,"key":"g","mouse":false,"round":19,"trial":58},{"type":"keyup","time":1348838,"key":"g","mouse":false,"round":19,"trial":58},{"type":"keydown","time":1349023,"key":"j","mouse":false,"round":19,"trial":58},{"type":"keyup","time":1349177,"key":"j","mouse":false,"round":19,"trial":58},{"type":"keydown","time":1349322,"key":"h","mouse":false,"round":19,"trial":58},{"type":"keyup","time":1349434,"key":"h","mouse":false,"round":19,"trial":58},{"type":"correctSequence","time":1349434,"sequence":"kgjh","round":19,"trial":58,"mouse":false},{"type":"lostRound","time":1349434,"round":19,"trial":58,"mouse":false,"activeProbability":0.5,"sequence":"kgjh","unchosenProbability":0.5,"mcsScore":0.20393223339931177},{"type":"startNextRound","time":1349434,"round":20,"trial":58,"mouse":false},{"type":"startNextRound","time":1352435,"round":23,"trial":58,"mouse":false},{"type":"startNextRound","time":1352436,"round":24,"trial":58,"mouse":false},{"type":"startNextRound","time":1352856,"round":19,"trial":59,"mouse":false},{"type":"keydown","time":1352856,"key":"g","mouse":false,"round":19,"trial":59},{"type":"keyup","time":1353092,"key":"g","mouse":false,"round":19,"trial":59},{"type":"keydown","time":1353278,"key":"j","mouse":false,"round":19,"trial":59},{"type":"keyup","time":1353401,"key":"j","mouse":false,"round":19,"trial":59},{"type":"keydown","time":1353582,"key":"h","mouse":false,"round":19,"trial":59},{"type":"keyup","time":1353680,"key":"h","mouse":false,"round":19,"trial":59},{"type":"keydown","time":1353858,"key":"k","mouse":false,"round":19,"trial":59},{"type":"keyup","time":1354006,"key":"k","mouse":false,"round":19,"trial":59},{"type":"correctSequence","time":1354006,"sequence":"gjhk","round":19,"trial":59,"mouse":false},{"type":"lostRound","time":1354006,"round":19,"trial":59,"mouse":false,"activeProbability":0.5,"sequence":"gjhk","unchosenProbability":0.5,"mcsScore":0.9651809723893128},{"type":"startNextRound","time":1354006,"round":20,"trial":59,"mouse":false},{"type":"startNextRound","time":1357008,"round":23,"trial":59,"mouse":false},{"type":"startNextRound","time":1357009,"round":24,"trial":59,"mouse":false},{"type":"startNextRound","time":1357585,"round":19,"trial":60,"mouse":false},{"type":"keydown","time":1357585,"key":"g","mouse":false,"round":19,"trial":60},{"type":"keyup","time":1357746,"key":"g","mouse":false,"round":19,"trial":60},{"type":"keydown","time":1357989,"key":"j","mouse":false,"round":19,"trial":60},{"type":"keyup","time":1358137,"key":"j","mouse":false,"round":19,"trial":60},{"type":"keydown","time":1358297,"key":"h","mouse":false,"round":19,"trial":60},{"type":"keyup","time":1358408,"key":"h","mouse":false,"round":19,"trial":60},{"type":"keydown","time":1358620,"key":"k","mouse":false,"round":19,"trial":60},{"type":"keyup","time":1358782,"key":"k","mouse":false,"round":19,"trial":60},{"type":"correctSequence","time":1358782,"sequence":"gjhk","round":19,"trial":60,"mouse":false},{"type":"winRound","time":1358782,"round":19,"trial":60,"mouse":false,"activeProbability":0.5,"sequence":"gjhk","unchosenProbability":0.5,"mcsScore":0.1891369334466969},{"type":"startNextRound","time":1358783,"round":21,"trial":60,"mouse":false},{"type":"startNextRound","time":1361783,"round":23,"trial":60,"mouse":false},{"type":"startNextRound","time":1361783,"round":24,"trial":60,"mouse":false},{"type":"startNextRound","time":1362476,"round":19,"trial":61,"mouse":false},{"type":"keydown","time":1362477,"key":"k","mouse":false,"round":19,"trial":61},{"type":"keyup","time":1362638,"key":"k","mouse":false,"round":19,"trial":61},{"type":"keydown","time":1362914,"key":"g","mouse":false,"round":19,"trial":61},{"type":"keyup","time":1363052,"key":"g","mouse":false,"round":19,"trial":61},{"type":"keydown","time":1363250,"key":"j","mouse":false,"round":19,"trial":61},{"type":"keyup","time":1363352,"key":"j","mouse":false,"round":19,"trial":61},{"type":"keydown","time":1363553,"key":"h","mouse":false,"round":19,"trial":61},{"type":"keyup","time":1363683,"key":"h","mouse":false,"round":19,"trial":61},{"type":"correctSequence","time":1363683,"sequence":"kgjh","round":19,"trial":61,"mouse":false},{"type":"lostRound","time":1363683,"round":19,"trial":61,"mouse":false,"activeProbability":0.5,"sequence":"kgjh","unchosenProbability":0.5,"mcsScore":0.022071632294914822},{"type":"startNextRound","time":1363683,"round":20,"trial":61,"mouse":false},{"type":"startNextRound","time":1366684,"round":23,"trial":61,"mouse":false},{"type":"startNextRound","time":1366684,"round":24,"trial":61,"mouse":false},{"type":"startNextRound","time":1367588,"round":19,"trial":62,"mouse":false},{"type":"keydown","time":1367589,"key":"g","mouse":false,"round":19,"trial":62},{"type":"keyup","time":1367762,"key":"g","mouse":false,"round":19,"trial":62},{"type":"keydown","time":1367979,"key":"j","mouse":false,"round":19,"trial":62},{"type":"keyup","time":1368121,"key":"j","mouse":false,"round":19,"trial":62},{"type":"keydown","time":1368268,"key":"h","mouse":false,"round":19,"trial":62},{"type":"keyup","time":1368358,"key":"h","mouse":false,"round":19,"trial":62},{"type":"keydown","time":1368516,"key":"k","mouse":false,"round":19,"trial":62},{"type":"keyup","time":1368653,"key":"k","mouse":false,"round":19,"trial":62},{"type":"correctSequence","time":1368653,"sequence":"gjhk","round":19,"trial":62,"mouse":false},{"type":"winRound","time":1368653,"round":19,"trial":62,"mouse":false,"activeProbability":0.5,"sequence":"gjhk","unchosenProbability":0.5,"mcsScore":0.18179791771625942},{"type":"startNextRound","time":1368653,"round":21,"trial":62,"mouse":false}]