[{"type":"startNextRound","time":2112583.5549999904,"round":23,"trial":152,"mouse":false},{"type":"startNextRound","time":2112583.660000004,"round":24,"trial":152,"mouse":false},{"type":"startNextRound","time":2113038.4049999993,"round":19,"trial":153,"mouse":false},{"type":"keydown","time":2113038.6399999843,"key":"k","mouse":false,"round":19,"trial":153},{"type":"keyup","time":2113198.1149999774,"key":"k","mouse":false,"round":19,"trial":153},{"type":"keydown","time":2113214.424999984,"key":"g","mouse":false,"round":19,"trial":153},{"type":"keyup","time":2113442.1199999927,"key":"g","mouse":false,"round":19,"trial":153},{"type":"keydown","time":2113592.579999997,"key":"h","mouse":false,"round":19,"trial":153},{"type":"keyup","time":2113698.1099999975,"key":"h","mouse":false,"round":19,"trial":153},{"type":"keydown","time":2113708.7849999955,"key":"j","mouse":false,"round":19,"trial":153},{"type":"keyup","time":2113889.0850000028,"key":"j","mouse":false,"round":19,"trial":153},{"type":"incorrectSequence","time":2113889.129999996,"sequence":"kghj","round":19,"trial":153,"mouse":false},{"type":"incorrectPlay","time":2113889.135000005,"round":19,"trial":153,"mouse":false,"activeProbability":0.5,"sequence":"kgjh","unchosenProbability":0.5,"mcsScore":0.21476181404466654},{"type":"startNextRound","time":2113889.284999983,"round":20,"trial":153,"mouse":false},{"type":"startNextRound","time":2116905.1199999815,"round":23,"trial":153,"mouse":false},{"type":"startNextRound","time":2116905.230000004,"round":24,"trial":153,"mouse":false},{"type":"startNextRound","time":2117247.174999997,"round":19,"trial":154,"mouse":false},{"type":"keydown","time":2117247.2949999794,"key":"k","mouse":false,"round":19,"trial":154},{"type":"keydown","time":2117389.614999993,"key":"g","mouse":false,"round":19,"trial":154},{"type":"keyup","time":2117410.499999998,"key":"k","mouse":false,"round":19,"trial":154},{"type":"keyup","time":2117559.334999998,"key":"g","mouse":false,"round":19,"trial":154},{"type":"keydown","time":2117720.949999988,"key":"j","mouse":false,"round":19,"trial":154},{"type":"keydown","time":2117864.7699999856,"key":"h","mouse":false,"round":19,"trial":154},{"type":"keyup","time":2117922.484999988,"key":"j","mouse":false,"round":19,"trial":154},{"type":"correctSequence","time":2117922.5299999816,"sequence":"kgjh","round":19,"trial":154,"mouse":false},{"type":"lostRound","time":2117922.5449999794,"round":19,"trial":154,"mouse":false,"activeProbability":0.5,"sequence":"kgjh","unchosenProbability":0.5,"mcsScore":0.16029662822360713},{"type":"startNextRound","time":2117922.599999991,"round":20,"trial":154,"mouse":false},{"type":"startNextRound","time":2120925.019999995,"round":23,"trial":154,"mouse":false},{"type":"startNextRound","time":2120925.359999994,"round":24,"trial":154,"mouse":false},{"type":"startNextRound","time":2121190.0599999935,"round":19,"trial":155,"mouse":false},{"type":"keydown","time":2121190.2049999917,"key":"g","mouse":false,"round":19,"trial":155},{"type":"keyup","time":2121369.2049999954,"key":"g","mouse":false,"round":19,"trial":155},{"type":"keydown","time":2121423.6300000045,"key":"j","mouse":false,"round":19,"trial":155},{"type":"keyup","time":2121603.8649999825,"key":"j","mouse":false,"round":19,"trial":155},{"type":"keydown","time":2121738.8249999788,"key":"h","mouse":false,"round":19,"trial":155},{"type":"keyup","time":2121876.2899999856,"key":"h","mouse":false,"round":19,"trial":155},{"type":"keydown","time":2121919.139999984,"key":"k","mouse":false,"round":19,"trial":155},{"type":"keyup","time":2122073.0000000037,"key":"k","mouse":false,"round":19,"trial":155},{"type":"correctSequence","time":2122073.0399999884,"sequence":"gjhk","round":19,"trial":155,"mouse":false},{"type":"lostRound","time":2122073.059999995,"round":19,"trial":155,"mouse":false,"activeProbability":0.5,"sequence":"gjhk","unchosenProbability":0.5,"mcsScore":0.5416522721537025},{"type":"startNextRound","time":2122073.0949999997,"round":20,"trial":155,"mouse":false},{"type":"startNextRound","time":2125074.995000003,"round":23,"trial":155,"mouse":false},{"type":"startNextRound","time":2125075.0999999875,"round":24,"trial":155,"mouse":false},{"type":"startNextRound","time":2125408.30499999,"round":19,"trial":156,"mouse":false},{"type":"keydown","time":2125408.429999981,"key":"k","mouse":false,"round":19,"trial":156},{"type":"keydown","time":2125544.689999981,"key":"g","mouse":false,"round":19,"trial":156},{"type":"keyup","time":2125565.6899999883,"key":"k","mouse":false,"round":19,"trial":156},{"type":"keyup","time":2125736.044999998,"key":"g","mouse":false,"round":19,"trial":156},{"type":"keydown","time":2125880.5699999793,"key":"j","mouse":false,"round":19,"trial":156},{"type":"keydown","time":2126055.009999982,"key":"h","mouse":false,"round":19,"trial":156},{"type":"keyup","time":2126112.504999997,"key":"j","mouse":false,"round":19,"trial":156},{"type":"correctSequence","time":2126112.6099999817,"sequence":"kgjh","round":19,"trial":156,"mouse":false},{"type":"lostRound","time":2126112.6799999913,"round":19,"trial":156,"mouse":false,"activeProbability":0.5,"sequence":"kgjh","unchosenProbability":0.5,"mcsScore":0.29321133004712974},{"type":"startNextRound","time":2126112.834999978,"round":20,"trial":156,"mouse":false},{"type":"startNextRound","time":2129120.2999999803,"round":23,"trial":156,"mouse":false},{"type":"startNextRound","time":2129120.43499999,"round":24,"trial":156,"mouse":false},{"type":"startNextRound","time":2129624.5899999924,"round":19,"trial":157,"mouse":false},{"type":"keydown","time":2129624.73499999,"key":"g","mouse":false,"round":19,"trial":157},{"type":"keyup","time":2129867.269999988,"key":"g","mouse":false,"round":19,"trial":157},{"type":"keydown","time":2129893.7199999928,"key":"k","mouse":false,"round":19,"trial":157},{"type":"keyup","time":2130052.9149999786,"key":"k","mouse":false,"round":19,"trial":157},{"type":"keydown","time":2130890.244999988,"key":"g","mouse":false,"round":19,"trial":157},{"type":"keydown","time":2130906.900000002,"key":"h","mouse":false,"round":19,"trial":157},{"type":"keyup","time":2130969.619999989,"key":"g","mouse":false,"round":19,"trial":157},{"type":"incorrectSequence","time":2130969.6649999823,"sequence":"gkgh","round":19,"trial":157,"mouse":false},{"type":"incorrectPlay","time":2130969.6750000003,"round":19,"trial":157,"mouse":false,"activeProbability":0.5,"sequence":"gjhk","unchosenProbability":0.5,"mcsScore":0.5184414708613239},{"type":"startNextRound","time":2130969.8149999892,"round":20,"trial":157,"mouse":false}]